protein_variant_nomenclature_parser/__init__.py
protein_variant_nomenclature_parser/hugo.py
protein_variant_nomenclature_parser/parser.py
protein_variant_nomenclature_parser/test_parser.py
protein_variant_nomenclature_parser-0.5.0.dist-info/LICENSE
protein_variant_nomenclature_parser-0.5.0.dist-info/METADATA
protein_variant_nomenclature_parser-0.5.0.dist-info/WHEEL
protein_variant_nomenclature_parser-0.5.0.dist-info/top_level.txt
protein_variant_nomenclature_parser-0.5.0.dist-info/RECORD
