Metadata-Version: 2.1
Name: protein-variant-nomenclature-parser
Version: 0.5.0
Summary: An ANTLR based parser for colloquial protein variant nomenclature
Home-page: https://github.com/tansey-lab/protein-variant-nomenclature-parser
Author: Jeff Quinn
Author-email: Jeff Quinn <quinnj2@mskcc.org>
Project-URL: Homepage, https://github.com/tansey-lab/protein-variant-nomenclature-parser
Project-URL: Bug Tracker, https://github.com/tansey-lab/protein-variant-nomenclature-parser/issues
Classifier: Programming Language :: Python :: 3
Classifier: License :: OSI Approved :: MIT License
Classifier: Operating System :: OS Independent
Requires-Python: >=3.7
License-File: LICENSE
